mylib_032/__init__.py
mylib_032-0.1.dist-info/LICENSE.txt
mylib_032-0.1.dist-info/METADATA
mylib_032-0.1.dist-info/WHEEL
mylib_032-0.1.dist-info/top_level.txt
mylib_032-0.1.dist-info/RECORD
