Metadata-Version: 2.1
Name: mylib-032
Version: 0.1
Summary: for calculating square
Author: Mr.Rohit
Author-email: rohit.chaudhari5945@gmail.com
License: UNKNOWN
Platform: UNKNOWN
Classifier: Programming Language :: Python :: 3
Classifier: License :: OSI Approved :: MIT License
Classifier: Operating System :: OS Independent
License-File: LICENSE.txt
